dealib/__init__.py
dealib/dea/__init__.py
dealib/dea/core/__init__.py
dealib/dea/core/_add.py
dealib/dea/core/_dea.py
dealib/dea/core/_direct.py
dealib/dea/core/_malmq.py
dealib/dea/core/_mea.py
dealib/dea/core/_sdea.py
dealib/dea/core/_slack.py
dealib/dea/utils/__init__.py
dealib/dea/utils/options.py
dealib/dea/utils/types.py
dealib/dea/utils/utils.py
dealib/dea/utils/wrappers.py
dealib/linprog/__init__.py
dealib/linprog/_simplex.py
dealib/linprog/_wrappers.py
dealib/linprog/tests/__init__.py
dealib/linprog/tests/reference/inequalities_1.json
dealib/linprog/tests/reference/inequalities_2.json
dealib/linprog/tests/reference/inequalities_3.json
dealib/linprog/tests/reference/inequalities_4.json
dealib/linprog/tests/reference/inequalities_5.json
dealib/linprog/tests/reference/inequalities_6.json
dealib/linprog/tests/reference/mixed_inequalities_1.json
dealib/linprog/tests/reference/mixed_inequalities_2.json
dealib/linprog/tests/reference/mixed_inequalities_and_equalities_1.json
dealib/linprog/tests/test_linprog.py
dealib/tests/__init__.py
dealib/tests/_test.py
dealib/tests/data/banks1/inputs.csv
dealib/tests/data/banks1/outputs.csv
dealib/tests/data/banks2/inputs.csv
dealib/tests/data/banks2/outputs.csv
dealib/tests/data/banks3/inputs.csv
dealib/tests/data/banks3/outputs.csv
dealib/tests/data/charnes/inputs.csv
dealib/tests/data/charnes/outputs.csv
dealib/tests/data/simple/inputs.csv
dealib/tests/data/simple/outputs.csv
dealib/tests/reference/add/banks1.json
dealib/tests/reference/add/charnes.json
dealib/tests/reference/add/simple.json
dealib/tests/reference/dea/banks1.json
dealib/tests/reference/dea/banks2.json
dealib/tests/reference/dea/banks3.json
dealib/tests/reference/dea/charnes.json
dealib/tests/reference/dea/simple.json
dealib/tests/reference/direct/banks1.json
dealib/tests/reference/direct/banks2.json
dealib/tests/reference/direct/banks3.json
dealib/tests/reference/direct/charnes.json
dealib/tests/reference/direct/simple.json
dealib-1.0.0.dist-info/LICENSE
dealib-1.0.0.dist-info/WHEEL
dealib-1.0.0.dist-info/METADATA
dealib-1.0.0.dist-info/RECORD
