Metadata-Version: 2.1
Name: dealib
Version: 1.0.0
Summary: Library developed in Python for conducting Data Envelopment Analysis (DEA).
Home-page: https://github.com/ArtyomViryutin/DEA
License: MIT
Keywords: benchmarking,data,envelopment,analysis,DEA
Author: Artyom Viryutin
Author-email: avviryutin@edu.hse.ru
Requires-Python: >=3.8,<4.0
Classifier: License :: OSI Approved :: MIT License
Classifier: Programming Language :: Python :: 3
Classifier: Programming Language :: Python :: 3.10
Classifier: Programming Language :: Python :: 3.8
Classifier: Programming Language :: Python :: 3.9
Requires-Dist: numpy (>=1.22.3,<2.0.0)
Project-URL: Repository, https://github.com/ArtyomViryutin/DEA
